Workbook

Sheet Executive Summary
A1: HDFC AMC — Financial Performance, Business Drivers & Relative Valuation Analysis
A2: FY2022–FY2026 | Excel-Based Financial Analysis
A4: Project Element | B4: Details
A5: Company | B5: HDFC Asset Management Company Ltd.
A6: Analysis Period | B6: FY2022–FY2026
A7: Primary Tool | B7: Microsoft Excel
A8: Analysis Type | B8: Financial Performance & Relative Valuation
A9: Peer Group | B9: Nippon Life AMC, UTI AMC, Aditya Birla Sun Life AMC
A10: Market Data Date | B10: 15 September 2026
A12: Key Analytical Framework
A13: Business Drivers → Financial Performance → Profitability → Cash Generation → Peer Comparison → Relative Valuation
A15: Executive Summary
A16: 1. | B16: Business Scale: HDFC AMC's closing AUM increased from ₹4.08 lakh crore in FY22 to ₹8.44 lakh crore in FY26, more than doubling over the analysis period.
A17: 2. | B17: Investor Expansion: Unique investors increased from 5.8 million in FY22 to 16.7 million in FY26, indicating significant expansion of the investor base.
A18: 3. | B18: Financial Performance: Revenue from operations and PAT increased substantially over FY22–FY26, with FY26 PAT reaching approximately ₹2,858 crore.
A19: 4. | B19: Financial Strength: HDFC AMC maintained a debt-free position while generating positive operating cash flow throughout the analysis period.
A20: 5. | B20: Relative Valuation: HDFC AMC trades at a premium to the selected AMC peers on P/E and P/B. The analysis indicates that strong profitability and earnings growth provide fundamental support for the premium, although the valuation remains an important risk factor.
A23: Tools & Analytical Methods
A25: Category | B25: Details
A26: Tool | B26: Microsoft Excel
A27: Financial Analysis | B27: Revenue, PAT, margins, ROE, ROA
A28: Growth Analysis | B28: YoY Growth, CAGR
A29: Business Drivers | B29: AUM, investor base, equity-oriented AUM
A30: Cash Flow Analysis | B30: Operating Cash Flow, Free Cash Flow
A31: Valuation | B31: P/E, P/B, Peer Median
A32: Peer Analysis | B32: Nippon Life AMC, UTI AMC, Aditya Birla Sun Life AMC
A33: Visualization | B33: Excel charts and trend analysis

Sheet Raw Data
A1: HDFC Asset Management Company Ltd.
A2: Financial Performance, Business Drivers & Relative Valuation Analysis
A3: Raw Financial Data — FY2022 to FY2026
A5: Financial Metric | B5: FY22 | C5: FY23 | D5: FY24 | E5: FY25 | F5: FY26
A6: Revenue from Operations | B6: 2115.36 | C6: 2166.81 | D6: 2584.37 | E6: 3498.03 | F6: 4118.53
A7: Other Income | B7: 317.84 | C7: 315.76 | D7: 578.06 | E7: 560.23 | F7: 498.73
A8: Total Income | B8: =B6+B7 -> 2433.2 | C8: =C6+C7 -> 2482.57 | D8: =D6+D7 -> 3162.43 | E8: =E6+E7 -> 4058.26 | F8: =F6+F7 -> 4617.26
A9: Total Expenses | B9: 577.91 | C9: 611.96 | D9: 684.24 | E9: 771.82 | F9: 907.08
A10: Profit Before Tax | B10: =B8-B9 -> 1855.29 | C10: =C8-C9 -> 1870.61 | D10: =D8-D9 -> 2478.19 | E10: =E8-E9 -> 3286.44 | F10: =F8-F9 -> 3710.18
A11: Profit After Tax | B11: 1393.13 | C11: 1423.92 | D11: 1945.88 | E11: 2461.05 | F11: 2858.06
A12: Total Assets | B12: 5880.37 | C12: 6536.53 | D12: 7557.55 | E12: 8753.63 | F12: 9988.39
A13: Total Equity / Net Worth | B13: 5530.04 | C13: 6108.41 | D13: 7079.07 | E13: 8134.14 | F13: 9231.09
A14: Interest-Bearing Debt | B14: 0 | C14: 0 | D14: 0 | E14: 0 | F14: 0
A16: Unit: ₹ crore, except where stated otherwise
A17: Source: HDFC Asset Management Company Ltd. Annual Reports FY2021–22 to FY2025–26 (hdfcfund.com/about-us/financial-information/annual-reports). Profit After Tax figures are as reported; other line items are as disclosed in the standalone financial statements.

Sheet Business Drivers
A1: Business Driver | B1: FY22 | C1: FY23 | D1: FY24 | E1: FY25 | F1: FY26
A2: Closing AUM (₹ crore) | B2: 407553 | C2: 436696 | D2: 607342 | E2: 754453 | F2: 844000
A3: Equity-Oriented AUM (₹ crore) | B3: 209000 | C3: 246000 | D3: 397000 | E3: 504000 | F3: 557500
A4: Unique Investors (million) | B4: 5.8 | C4: 6.6 | D4: 9.6 | E4: 13.2 | F4: 16.7
A5: Live Accounts (million) | B5: 9.9 | C5: 11.4 | D5: 16.6 | E5: 23.3 | F5: 30.2
A6: Overall AUM Market Share (%) | B6: - | C6: - | D6: - | E6: 0.115 | F6: -
A7: Active Equity Market Share (%) | B7: - | C7: - | D7: - | E7: 0.129 | F7: 0.13
A9: SIP AUM / Systematic AUM (₹ crore) | B9: - | C9: - | D9: - | E9: - | F9: 200,000+
A10: Digital Transactions (%) | B10: 0.76 | C10: 0.81 | D10: 0.9 | E10: 0.94 | F10: -
A12: Source: HDFC AMC FY2024–25 and FY2025–26 Annual Reports / investor disclosures. FY26 SIP AUM is reported as crossing ₹2 trillion.

Sheet Growth Analysis
A1: Metric | B1: FY23 | C1: FY24 | D1: FY25 | E1: FY26 | F1: FY22–FY26 CAGR
A2: Revenue Growth | B2: ='Raw Data'!C6/'Raw Data'!B6-1 -> 0.024322101 | C2: ='Raw Data'!D6/'Raw Data'!C6-1 -> 0.19270725 | D2: ='Raw Data'!E6/'Raw Data'!D6-1 -> 0.35353297 | E2: ='Raw Data'!F6/'Raw Data'!E6-1 -> 0.17738556 | F2: =('Raw Data'!F6/'Raw Data'!B6)^(1/4)-1 -> 0.18124365
A3: Total Income Growth | B3: ='Raw Data'!C8/'Raw Data'!B8-1 -> 0.020290153 | C3: ='Raw Data'!D8/'Raw Data'!C8-1 -> 0.27385331 | D3: ='Raw Data'!E8/'Raw Data'!D8-1 -> 0.28327267 | E3: ='Raw Data'!F8/'Raw Data'!E8-1 -> 0.13774376 | F3: =('Raw Data'!F8/'Raw Data'!B8)^(1/4)-1 -> 0.17368521
A4: PAT Growth | B4: ='Raw Data'!C11/'Raw Data'!B11-1 -> 0.022101311 | C4: ='Raw Data'!D11/'Raw Data'!C11-1 -> 0.36656554 | D4: ='Raw Data'!E11/'Raw Data'!D11-1 -> 0.26474911 | E4: ='Raw Data'!F11/'Raw Data'!E11-1 -> 0.16131732 | F4: =('Raw Data'!F11/'Raw Data'!B11)^(1/4)-1 -> 0.19679544
A5: AUM Growth | B5: ='Business Drivers'!C2/'Business Drivers'!B2-1 -> 0.071507264 | C5: ='Business Drivers'!D2/'Business Drivers'!C2-1 -> 0.39076612 | D5: ='Business Drivers'!E2/'Business Drivers'!D2-1 -> 0.24222102 | E5: ='Business Drivers'!F2/'Business Drivers'!E2-1 -> 0.11869129 | F5: =('Business Drivers'!F2/'Business Drivers'!B2)^(1/4)-1 -> 0.19960865
A6: Equity-Oriented AUM Growth | B6: ='Business Drivers'!C3/'Business Drivers'!B3-1 -> 0.17703349 | C6: ='Business Drivers'!D3/'Business Drivers'!C3-1 -> 0.61382114 | D6: ='Business Drivers'!E3/'Business Drivers'!D3-1 -> 0.26952141 | E6: ='Business Drivers'!F3/'Business Drivers'!E3-1 -> 0.10615079 | F6: =('Business Drivers'!F3/'Business Drivers'!B3)^(1/4)-1 -> 0.27798173
A7: Investor Growth | B7: ='Business Drivers'!C4/'Business Drivers'!B4-1 -> 0.13793103 | C7: ='Business Drivers'!D4/'Business Drivers'!C4-1 -> 0.45454545 | D7: ='Business Drivers'!E4/'Business Drivers'!D4-1 -> 0.375 | E7: ='Business Drivers'!F4/'Business Drivers'!E4-1 -> 0.26515152 | F7: =('Business Drivers'!F4/'Business Drivers'!B4)^(1/4)-1 -> 0.30263313
A9: All growth figures are calculated year-over-year from the Raw Data and Business Drivers sheets. CAGR = (FY26 value / FY22 value)^(1/4) - 1.

Sheet Profitability
A1: Profitability Metric | B1: FY22 | C1: FY23 | D1: FY24 | E1: FY25 | F1: FY26
A2: Operating Profit Margin | B2: =('Raw Data'!B8-'Raw Data'!B7-'Raw Data'!B9)/'Raw Data'!B6 -> 0.726803 | C2: =('Raw Data'!C8-'Raw Data'!C7-'Raw Data'!C9)/'Raw Data'!C6 -> 0.71757561 | D2: =('Raw Data'!D8-'Raw Data'!D7-'Raw Data'!D9)/'Raw Data'!D6 -> 0.73523915 | E2: =('Raw Data'!E8-'Raw Data'!E7-'Raw Data'!E9)/'Raw Data'!E6 -> 0.77935581 | F2: =('Raw Data'!F8-'Raw Data'!F7-'Raw Data'!F9)/'Raw Data'!F6 -> 0.77975637
A3: Net Profit Margin | B3: ='Raw Data'!B11/'Raw Data'!B6 -> 0.65857821 | C3: ='Raw Data'!C11/'Raw Data'!C6 -> 0.65715037 | D3: ='Raw Data'!D11/'Raw Data'!D6 -> 0.75294172 | E3: ='Raw Data'!E11/'Raw Data'!E6 -> 0.70355314 | F3: ='Raw Data'!F11/'Raw Data'!F6 -> 0.69395148
A4: ROE | B4: N/A | C4: ='Raw Data'!C11/AVERAGE('Raw Data'!B13,'Raw Data'!C13) -> 0.24469238 | D4: ='Raw Data'!D11/AVERAGE('Raw Data'!C13,'Raw Data'!D13) -> 0.29511021 | E4: ='Raw Data'!E11/AVERAGE('Raw Data'!D13,'Raw Data'!E13) -> 0.32354119 | F4: ='Raw Data'!F11/AVERAGE('Raw Data'!E13,'Raw Data'!F13) -> 0.32917042
A5: ROA | B5: N/A | C5: ='Raw Data'!C11/AVERAGE('Raw Data'!B12,'Raw Data'!C12) -> 0.22935193 | D5: ='Raw Data'!D11/AVERAGE('Raw Data'!C12,'Raw Data'!D12) -> 0.27612728 | E5: ='Raw Data'!E11/AVERAGE('Raw Data'!D12,'Raw Data'!E12) -> 0.30176235 | F5: ='Raw Data'!F11/AVERAGE('Raw Data'!E12,'Raw Data'!F12) -> 0.30498954
A7: Operating Profit = Total Income − Other Income − Total Expenses, margin on Revenue from Operations. Net Profit Margin = Profit After Tax ÷ Revenue from Operations (matches company-reported convention). ROE and ROA use average (opening + closing) equity/assets; FY25 company-reported figures: Operating Profit Margin 77.94%, Net Profit Margin 70.36%, ROE 32.35% (HDFC AMC FY2024–25 Annual Report) — this workbook's FY25 formulas reproduce those figures. FY22 ROE and ROA are shown as N/A because the average-balance calculation needs an FY21 opening equity/assets figure, which is outside this workbook's FY22–FY26 data range. (no FY21 opening balance available)

Sheet Cash Flow & Strength
A1: Cash Flow Metric | B1: FY22 | C1: FY23 | D1: FY24 | E1: FY25 | F1: FY26
A2: Operating Cash Flow | B2: 1253.73 | C2: 1149.32 | D2: 1620.01 | E2: 2076.7 | F2: 2530.09
A3: Capital Expenditure | B3: 10.23 | C3: 14.1 | D3: 18.56 | E3: 44.76 | F3: Not Verified
A4: Free Cash Flow | B4: =B2-B3 -> 1243.5 | C4: =C2-C3 -> 1135.22 | D4: =D2-D3 -> 1601.45 | E4: =E2-E3 -> 2031.94 | F4: N/A
A5: Cash & Cash Equivalents | B5: - | C5: - | D5: 10.21 | E5: 11.58 | F5: 10.97
A6: Interest-Bearing Debt | B6: 0 | C6: 0 | D6: 0 | E6: 0 | F6: 0
A8: Financial Strength Indicators
A9: Indicator | B9: FY22 | C9: FY23 | D9: FY24 | E9: FY25 | F9: FY26
A10: Debt-Free Status | B10: Yes | C10: Yes | D10: Yes | E10: Yes | F10: Yes
A11: Current Ratio | B11: - | C11: - | D11: 6.78 | E11: 8.03 | F11: -
A13: Source: HDFC AMC FY2022–23 and FY2024–25 Annual Reports (cash-flow statements) and FY2025–26 standalone results. Capital expenditure = purchase of property, plant & equipment and intangible assets. Debt/Equity and Interest Coverage are not presented because the company carries no interest-bearing debt. FY26 capital expenditure and free cash flow are shown as N/A because FY26 capex had not yet been disclosed in the standalone financial statements available at the time of this analysis.

Sheet Peer Comparison
A1: Metric | B1: HDFC AMC | C1: Nippon Life AMC | D1: UTI AMC | E1: Aditya Birla Sun Life AMC
A2: Operating Revenue / Revenue from Operations (₹ Cr) | B2: ='Raw Data'!F6 -> 4118.53 | C2: 2924 | D2: 1705 | E2: 1845.03
A3: Profit After Tax (₹ Cr) | B3: ='Raw Data'!F11 -> 2858.06 | C3: 1529 | D3: 472 | E3: 975.07
A4: ROE (%) | B4: =Profitability!F4 -> 0.32917042 | C4: 0.345 | D4: 0.103 | E4: 0.2553
A5: Net Profit Margin (%) | B5: =B3/B2 -> 0.69395148 | C5: =C3/C2 -> 0.52291382 | D5: =D3/D2 -> 0.27683284 | E5: =E3/E2 -> 0.52848463
A6: Market Capitalisation (₹ Cr) — as of 15 Sep 2026 | B6: 103257.58 | C6: 75632 | D6: 11800 | E6: 26053.65
A7: P/E (x) — as of 15 Sep 2026 | B7: 35.03 | C7: 46.6 | D7: 27 | E7: 26.02
A8: P/B (x) — as of 15 Sep 2026 | B8: 11.19 | C8: 16.36 | D8: 2.7 | E8: 6.28
A10: Peer Growth Data (for PAT CAGR calculation)
A11: Metric | B11: HDFC AMC | C11: Nippon Life AMC | D11: UTI AMC | E11: Aditya Birla Sun Life AMC
A12: FY22 PAT (₹ Cr) | B12: - | C12: 744 | D12: 417.78 | E12: 672.77
A13: FY26 PAT (₹ Cr) (linked) | B13: =B3 -> 2858.06 | C13: =C3 -> 1529 | D13: =D3 -> 472 | E13: =E3 -> 975.07
A15: Peer FY26 operating revenue, PAT and ROE are from each company's FY2025–26 annual report / directors' report (Nippon Life India AMC, UTI AMC, Aditya Birla Sun Life AMC). HDFC AMC figures are linked from the Raw Data and Profitability sheets. Market capitalisation, P/E and P/B are market-price snapshots as of 15 September 2026 and will change with the share price. FY22 peer PAT figures are from each company's FY2021–22 annual report.

Sheet Valuation
A1: Valuation Metric | B1: HDFC AMC | C1: Peer Median | D1: HDFC AMC Premium / Discount
A2: P/E | B2: ='Peer Comparison'!B7 -> 35.03 | C2: =MEDIAN('Peer Comparison'!C7:E7) -> 27 | D2: =B2/C2-1 -> 0.29740741
A3: P/B | B3: ='Peer Comparison'!B8 -> 11.19 | C3: =MEDIAN('Peer Comparison'!C8:E8) -> 6.28 | D3: =B3/C3-1 -> 0.78184713
A5: Fundamental Comparison
A6: Fundamental Metric | B6: HDFC AMC | C6: Peer Median | D6: HDFC AMC vs Peer Median
A7: ROE | B7: ='Peer Comparison'!B4 -> 0.32917042 | C7: =MEDIAN('Peer Comparison'!C4:E4) -> 0.2553 | D7: =B7-C7 -> 0.073870417
A8: Net Profit Margin | B8: ='Peer Comparison'!B5 -> 0.69395148 | C8: =MEDIAN('Peer Comparison'!C5:E5) -> 0.52291382 | D8: =B8-C8 -> 0.17103767
A9: PAT CAGR (FY22–FY26) | B9: ='Growth Analysis'!F4 -> 0.19679544 | C9: =MEDIAN(B14:D14) -> 0.09721641 | D9: =B9-C9 -> 0.099579026
A10: AUM CAGR (FY22–FY26) | B10: ='Growth Analysis'!F5 -> 0.19960865 | C10: - | D10: -
A13: Peer PAT CAGR (helper) | B13: Nippon Life AMC | C13: UTI AMC | D13: Aditya Birla Sun Life AMC
A14: FY22–FY26 PAT CAGR | B14: =('Peer Comparison'!C13/'Peer Comparison'!C12)^(1/4)-1 -> 0.19731559 | C14: =('Peer Comparison'!D13/'Peer Comparison'!D12)^(1/4)-1 -> 0.030976078 | D14: =('Peer Comparison'!E13/'Peer Comparison'!E12)^(1/4)-1 -> 0.09721641
A16: Peer P/E and P/B medians exclude HDFC AMC. AUM CAGR peer median is intentionally left blank because peers disclose AUM on different bases (closing AUM vs. quarterly-average AUM), which would make a direct comparison misleading.
A18: Valuation Summary
A19: Valuation Indicator | B19: HDFC AMC | C19: Peer Median
A20: P/E | B20: =B2 -> 35.03 | C20: =C2 -> 27
A21: P/B | B21: =B3 -> 11.19 | C21: =C3 -> 6.28
A22: ROE | B22: =B7 -> 0.32917042 | C22: =C7 -> 0.2553
A23: Net Profit Margin | B23: =B8 -> 0.69395148 | C23: =C8 -> 0.52291382
A24: PAT CAGR | B24: =B9 -> 0.19679544 | C24: =C9 -> 0.09721641
A26: Overall Valuation View | B26: HDFC AMC trades at a premium to the peer median on both P/E and P/B. This premium is partly supported by superior ROE, net profit margin and PAT CAGR versus peers, but it also leaves less room for disappointment if growth moderates.

Sheet Insights
A1: HDFC AMC — Key Financial & Valuation Insights
A3: Insight Area | B3: Key Finding
A4: Revenue Growth | B4: Revenue from operations increased strongly from FY22 to FY26, supported by the expansion of HDFC AMC's business scale.
A5: PAT Growth | B5: Profit after tax increased substantially over FY22–FY26, demonstrating strong earnings growth.
A6: AUM Growth | B6: Closing AUM increased from ₹4.08 lakh crore in FY22 to ₹8.44 lakh crore in FY26, more than doubling over the period.
A7: Profitability | B7: HDFC AMC maintained strong profitability, with high operating and net profit margins and a consistently strong ROE.
A8: Cash Generation | B8: Operating cash flow remained positive throughout FY22–FY26 and increased to ₹2,530.09 crore in FY26.
A9: Financial Strength | B9: HDFC AMC remained debt-free throughout the period, supporting a strong financial position.
A10: Valuation | B10: HDFC AMC trades at a premium to the peer median on P/E and P/B, so the premium needs to be assessed against its superior profitability and earnings growth.
A12: Key Risks & Limitations
A13: Area | B13: Observation
A14: Market Dependence | B14: AMC revenues and AUM are influenced by equity-market performance and investor sentiment.
A15: Valuation Risk | B15: A high P/E and P/B multiple leaves less room for disappointment if future growth slows.
A16: Peer Comparability | B16: Peer AUM disclosures can use different measures such as closing AUM and QAAUM, so AUM comparisons require caution.
A17: Other Income | B17: Total income includes other income, which can fluctuate and should not be treated as recurring operating revenue.
A18: Market Data | B18: Valuation multiples are market-price dependent and can change daily.
A20: Investment & Business Conclusion
A21: HDFC Asset Management Company demonstrated strong financial and business performance between FY22 and FY26, supported by substantial AUM expansion, increasing profitability, strong cash generation and a debt-free balance sheet. The company's earnings growth and operating performance indicate that the expansion in business scale has translated into stronger financial results. Relative valuation analysis shows that HDFC AMC trades at a premium to the selected AMC peers on P/E and P/B. This premium is supported to an extent by its strong profitability, ROE and earnings growth; however, the elevated valuation also creates downside risk if future earnings or AUM growth moderates. Therefore, the analysis suggests that HDFC AMC's premium valuation reflects the quality and strength of its underlying fundamentals, but the valuation leaves limited room for execution or growth disappointments. Overall, HDFC AMC presents a strong combination of business scale, profitability, financial strength and growth, while its premium valuation remains the key factor that investors need to monitor.
